SurveyGizmo-1.2.3.dist-info/DESCRIPTION.rst
SurveyGizmo-1.2.3.dist-info/METADATA
SurveyGizmo-1.2.3.dist-info/RECORD
SurveyGizmo-1.2.3.dist-info/WHEEL
SurveyGizmo-1.2.3.dist-info/metadata.json
SurveyGizmo-1.2.3.dist-info/top_level.txt
surveygizmo/__init__.py
surveygizmo/compat.py
surveygizmo/surveygizmo.py
surveygizmo/api/__init__.py
surveygizmo/api/account.py
surveygizmo/api/accountteams.py
surveygizmo/api/accountuser.py
surveygizmo/api/base.py
surveygizmo/api/contact.py
surveygizmo/api/contactlist.py
surveygizmo/api/emailmessage.py
surveygizmo/api/survey.py
surveygizmo/api/surveycampaign.py
surveygizmo/api/surveyoption.py
surveygizmo/api/surveypage.py
surveygizmo/api/surveyquestion.py
surveygizmo/api/surveyreport.py
surveygizmo/api/surveyresponse.py
surveygizmo/api/surveystatistic.py
tests/__init__.py
tests/test_api.py
tests/test_resource.py
tests/test_surveygizmo.py
