Metadata-Version: 1.1
Name: SurveyGizmo
Version: 1.2.3
Summary: A Python Wrapper for SurveyGizmo's restful API service.
Home-page: https://github.com/ITNG/SurveyGizmo/
Author: Ryan P Kilby
Author-email: rpkilby@ncsu.edu
License: BSD License
Keywords: Survey Gizmo SurveyGizmo surveygizmo
Platform: UNKNOWN
Classifier: Development Status :: 4 - Beta
Classifier: Environment :: Web Environment
Classifier: Intended Audience :: Developers
Classifier: Programming Language :: Python
Classifier: Programming Language :: Python :: 2
Classifier: Programming Language :: Python :: 2.7
Classifier: Programming Language :: Python :: 3
Classifier: Programming Language :: Python :: 3.4
Classifier: Programming Language :: Python :: 3.5
Classifier: Programming Language :: Python :: 3.6
Classifier: License :: OSI Approved :: BSD License
Classifier: Operating System :: OS Independent
Classifier: Topic :: Internet :: WWW/HTTP
Classifier: Topic :: Software Development :: Libraries :: Python Modules
